Cipher/AES.py
Cipher/ARC2.py
Cipher/ARC4.py
Cipher/Blowfish.py
Cipher/CAST.py
Cipher/ChaCha20.py
Cipher/ChaCha20_Poly1305.py
Cipher/DES.py
Cipher/DES3.py
Cipher/PKCS1_OAEP.py
Cipher/PKCS1_v1_5.py
Cipher/Salsa20.py
Cipher/_EKSBlowfish.py
Cipher/__init__.py
Cipher/_mode_cbc.py
Cipher/_mode_ccm.py
Cipher/_mode_cfb.py
Cipher/_mode_ctr.py
Cipher/_mode_eax.py
Cipher/_mode_ecb.py
Cipher/_mode_gcm.py
Cipher/_mode_ocb.py
Cipher/_mode_ofb.py
Cipher/_mode_openpgp.py
Cipher/_mode_siv.py
Hash/BLAKE2b.py
Hash/BLAKE2s.py
Hash/CMAC.py
Hash/HMAC.py
Hash/KMAC128.py
Hash/KMAC256.py
Hash/KangarooTwelve.py
Hash/MD2.py
Hash/MD4.py
Hash/MD5.py
Hash/Poly1305.py
Hash/RIPEMD.py
Hash/RIPEMD160.py
Hash/SHA.py
Hash/SHA1.py
Hash/SHA224.py
Hash/SHA256.py
Hash/SHA384.py
Hash/SHA3_224.py
Hash/SHA3_256.py
Hash/SHA3_384.py
Hash/SHA3_512.py
Hash/SHA512.py
Hash/SHAKE128.py
Hash/SHAKE256.py
Hash/TupleHash128.py
Hash/TupleHash256.py
Hash/__init__.py
Hash/cSHAKE128.py
Hash/cSHAKE256.py
Hash/keccak.py
Math/Numbers.py
Math/Primality.py
Math/_IntegerBase.py
Math/_IntegerCustom.py
Math/_IntegerGMP.py
Math/_IntegerNative.py
Math/__init__.py
PublicKey/DSA.py
PublicKey/ECC.py
PublicKey/ElGamal.py
PublicKey/RSA.py
PublicKey/__init__.py
PublicKey/_openssh.py
Random/__init__.py
Random/random.py
Signature/DSS.py
Signature/PKCS1_PSS.py
Signature/PKCS1_v1_5.py
Signature/__init__.py
Signature/eddsa.py
Signature/pkcs1_15.py
Signature/pss.py
cryptotext/__init__.py
cryptotext/ptc.py
cryptotext/pth.py
cryptotext/snm.py
library/__init__.py
library/cryptor.py
library/hash.py
library/package.py
cryptotext-0.2.dist-info/LICENSE
cryptotext-0.2.dist-info/METADATA
cryptotext-0.2.dist-info/WHEEL
cryptotext-0.2.dist-info/top_level.txt
cryptotext-0.2.dist-info/RECORD
